README.md
pyproject.toml
setup.py
agents/__init__.py
agents/agent.py
agents/message.py
agents/storage.py
agents/utils.py
agents/version.py
agents/mixins/__init__.py
agents/mixins/authentication.py
agents/mixins/notifications.py
agents/mixins/router_client.py
agents/mixins/webserver.py
examples/__init__.py
examples/asyncio_interop.py
examples/curve_auth.py
examples/echo_server.py
examples/notifications.py
examples/router_client.py
examples/simple_agent.py
examples/websocket_echo_server.py
examples/zap_curve_auth.py
powerful_agents.egg-info/PKG-INFO
powerful_agents.egg-info/SOURCES.txt
powerful_agents.egg-info/dependency_links.txt
powerful_agents.egg-info/not-zip-safe
powerful_agents.egg-info/requires.txt
powerful_agents.egg-info/top_level.txt